{
  "title": "Machine Learning - Chapter 11",
  "description": "Run Python Code with Jupyter Notebooks",
  "difficulty": "Beginner",
  "time": "10 minutes",
  "details": {
    "steps": [{
      "title": "Jupyter Notebook",
      "text": "steps/1/text.md"
    },
 {
      "title": "Gini Index",
      "text": "steps/2/text.md"
    },    
	{
      "title": "Create Split",
      "text": "steps/3/text.md"
    },
	{
      "title": "Build a Tree",
      "text": "steps/4/text.md"
    },
    {
      "title": "Make a Prediction",
      "text": "steps/5/text.md"
      },
    {
      "title": "Banknote Case Study",
      "text": "steps/6/text.md"
    }],
    "intro": {
      "text": "intro.md",
      "code": "set-env.sh"
    },
    "finish": {
      "text": "finish.md"
    },
    "assets": {
      "client": [
        {"file": "prepareContainer.sh"                  ,"target": "~/"},
        {"file": "data_banknote_authentication.csv"     ,"target": "~/"},
        {"file": "gini_split.ipynb"                     ,"target": "~/"},
        {"file": "cart_banknote.ipynb"                  ,"target": "~/"},
        {"file": "split_dataset.ipynb"                  ,"target": "~/"},
        {"file": "create_tree.ipynb"                    ,"target": "~/"},
        {"file": "make_prediction.ipynb"                ,"target": "~/"}
      ]
    }
  },
  "environment": {
    "uilayout": "terminal-iframe",
    "showdashboard": true,
    "dashboards": [
      {
        "name": "Jupyter Notebook",
        "port": 8888
      }
    ],
    "uimessage1": "\u001b[32mYour Interactive Bash Terminal.\r\n"
  },
  "backend": {
    "imageid": "docker"
  }
}